[
  {
    "product": "GALAXY WATCH",
    "CPU": "Dual-Core",
    "RAM": "1.5 GB",
    "SSD": "7.6 GB",
    "weight": "30.3 g",
    "display": "34.6 mm",
    "OS": "Wear OS Powered by Samsung",
    "AS": "6개월"
  },
  {
    "product": "GALAXY WATCH",
    "CPU": "Dual-Core",
    "RAM": "1.5 GB",
    "SSD": "7.6 GB",
    "weight": "30.3 g",
    "display": "34.6 mm",
    "OS": "Wear OS Powered by Samsung",
    "AS": "6개월"
  },
  {
    "product": "GALAXY WATCH",
    "CPU": "Dual-Core",
    "RAM": "1.5 GB",
    "SSD": "7.6 GB",
    "weight": "30.3 g",
    "display": "34.6 mm",
    "OS": "Wear OS Powered by Samsung",
    "AS": "6개월"
  }
]